logtree/__init__.py
logtree/logtree.py
logtree-1.1.dist-info/LICENSE
logtree-1.1.dist-info/WHEEL
logtree-1.1.dist-info/METADATA
logtree-1.1.dist-info/RECORD
